topsis/__init__.py
topsis/__main__.py
Topsis_Lakshit_102203222-1.0.0.dist-info/LICENSE
Topsis_Lakshit_102203222-1.0.0.dist-info/METADATA
Topsis_Lakshit_102203222-1.0.0.dist-info/WHEEL
Topsis_Lakshit_102203222-1.0.0.dist-info/entry_points.txt
Topsis_Lakshit_102203222-1.0.0.dist-info/top_level.txt
Topsis_Lakshit_102203222-1.0.0.dist-info/RECORD
