Metadata-Version: 2.2
Name: Topsis-Lakshit-102203222
Version: 1.0.0
Summary: It does the mathematics of topsis
Home-page: https://github.com/Lakshit78/Topsis-Lakshit-102203222
Author: Lakshit Gupta
Author-email: lakshitajaygupta@gmail.com
License: MIT
Classifier: License :: OSI Approved :: MIT License
Classifier: Programming Language :: Python :: 3.6
Classifier: Programming Language :: Python :: 3.7
Classifier: Programming Language :: Python :: 3.8
Classifier: Programming Language :: Python :: 3.9
Classifier: Programming Language :: Python :: 3.10
Classifier: Programming Language :: Python :: 3.11
Classifier: Programming Language :: Python :: 3.12
License-File: LICENSE
Dynamic: author
Dynamic: author-email
Dynamic: classifier
Dynamic: description
Dynamic: description-content-type
Dynamic: home-page
Dynamic: license
Dynamic: summary
